<?xml version="1.0" encoding="UTF-8"?>
<!DOCTYPE properties SYSTEM "http://java.sun.com/dtd/properties.dtd">

<!--  Licensed to the Apache Software Foundation (ASF) under one
  or more contributor license agreements.  See the NOTICE file
  distributed with this work for additional information
  regarding copyright ownership.  The ASF licenses this file
  to you under the Apache License, Version 2.0 (the
  "License"); you may not use this file except in compliance
  with the License.  You may obtain a copy of the License at

      http://www.apache.org/licenses/LICENSE-2.0

  Unless required by applicable law or agreed to in writing,
  software distributed under the License is distributed on an
  "AS IS" BASIS, WITHOUT WARRANTIES OR CONDITIONS OF ANY
  KIND, either express or implied.  See the License for the
  specific language governing permissions and limitations
  under the License.

#####################################################################
 This File is auto-generated by the LanguageEditor
 to add new Languages or modify/customize it use the LanguageEditor
 see https://openmeetings.apache.org/LanguageEditor.html for Details
#####################################################################
-->
<properties>
	<entry key="4"><![CDATA[Nastavenia]]></entry>
	<entry key="5"><![CDATA[Profil]]></entry>
	<entry key="6"><![CDATA[Administrácia]]></entry>
	<entry key="15"><![CDATA[Nahrať súbor]]></entry>
	<entry key="18"><![CDATA[Nové hlasovanie]]></entry>
	<entry key="19"><![CDATA[Nové hlasovanie pre konferenciu]]></entry>
	<entry key="20"><![CDATA[Otázka]]></entry>
	<entry key="21"><![CDATA[Typ hlasovania]]></entry>
	<entry key="22"><![CDATA[Vytvoriť]]></entry>
	<entry key="23"><![CDATA[Všetci pripojení používatelia prijímajú správu s novým hlasovaním]]></entry>
	<entry key="24"><![CDATA[Vytvoriť hlasovanie]]></entry>
	<entry key="32"><![CDATA[Hlasovať]]></entry>
	<entry key="33"><![CDATA[Vaša odpoveď]]></entry>
	<entry key="34"><![CDATA[Áno]]></entry>
	<entry key="35"><![CDATA[Nie]]></entry>
	<entry key="36"><![CDATA[chce vedieť]]></entry>
	<entry key="37"><![CDATA[Výsledky hlasovania]]></entry>
	<entry key="39"><![CDATA[Výsledky]]></entry>
	<entry key="40"><![CDATA[Odpovede]]></entry>
	<entry key="45"><![CDATA[Typ]]></entry>
	<entry key="51"><![CDATA[Vybrať zariadenie]]></entry>
	<entry key="52"><![CDATA[Vybrať webkameru]]></entry>
	<entry key="53"><![CDATA[Vybrať mikrofón]]></entry>
	<entry key="54"><![CDATA[OK]]></entry>
	<entry key="59"><![CDATA[Jazyk]]></entry>
	<entry key="62"><![CDATA[Zmazať tabuľu]]></entry>
	<entry key="72"><![CDATA[Vybrať objekt]]></entry>
	<entry key="73"><![CDATA[Text]]></entry>
	<entry key="74"><![CDATA[Farba]]></entry>
	<entry key="75"><![CDATA[Nakresliť čiaru]]></entry>
	<entry key="76"><![CDATA[Highlighter]]></entry>
	<entry key="77"><![CDATA[Obdĺžnik]]></entry>
	<entry key="78"><![CDATA[Elipsa]]></entry>
	<entry key="79"><![CDATA[Šípka]]></entry>
	<entry key="80"><![CDATA[Zmazať vybranú položku]]></entry>
	<entry key="82"><![CDATA[Flexible textbox]]></entry>
	<entry key="84"><![CDATA[Nemám otázku]]></entry>
	<entry key="85"><![CDATA[Zatvoriť]]></entry>
	<entry key="86"><![CDATA[ležatý]]></entry>
	<entry key="87"><![CDATA[hrubý]]></entry>
	<entry key="98"><![CDATA[Moderátor]]></entry>
	<entry key="99"><![CDATA[Táto miestnosť je už obsadená]]></entry>
	<entry key="108"><![CDATA[Prihlásenie]]></entry>
	<entry key="109"><![CDATA[Meno a email]]></entry>
	<entry key="110"><![CDATA[Heslo]]></entry>
	<entry key="112"><![CDATA[Prihlásiť sa]]></entry>
	<entry key="113"><![CDATA[Zaregistrovať sa]]></entry>
	<entry key="114"><![CDATA[Používateľské meno]]></entry>
	<entry key="116"><![CDATA[Znova heslo]]></entry>
	<entry key="117"><![CDATA[Meno]]></entry>
	<entry key="119"><![CDATA[Email]]></entry>
	<entry key="121"><![CDATA[Registrovať]]></entry>
	<entry key="123"><![CDATA[Nie ste členom?]]></entry>
	<entry key="124"><![CDATA[Domov]]></entry>
	<entry key="125"><![CDATA[Používatelia]]></entry>
	<entry key="126"><![CDATA[Skupiny]]></entry>
	<entry key="135"><![CDATA[Titul/Meno]]></entry>
	<entry key="136"><![CDATA[Priezvisko]]></entry>
	<entry key="138"><![CDATA[Narodeniny]]></entry>
	<entry key="139"><![CDATA[Ulica/Číslo]]></entry>
	<entry key="140"><![CDATA[PSČ/Mesto]]></entry>
	<entry key="141"><![CDATA[Krajina]]></entry>
	<entry key="142"><![CDATA[Adresa]]></entry>
	<entry key="143"><![CDATA[Údaje používateľa]]></entry>
	<entry key="144"><![CDATA[Uložiť]]></entry>
	<entry key="155"><![CDATA[Nové nahrávanie]]></entry>
	<entry key="157"><![CDATA[Zmazať nahrávku]]></entry>
	<entry key="159"><![CDATA[Zablokované]]></entry>
	<entry key="161"><![CDATA[Spoločnosti]]></entry>
	<entry key="162"><![CDATA[Kalendár]]></entry>
	<entry key="165"><![CDATA[Meno]]></entry>
	<entry key="177"><![CDATA[Používateľ]]></entry>
	<entry key="178"><![CDATA[Pridať používateľa]]></entry>
	<entry key="186"><![CDATA[Miestnosť]]></entry>
	<entry key="188"><![CDATA[ID]]></entry>
	<entry key="190"><![CDATA[Verejné]]></entry>
	<entry key="196"><![CDATA[Komentovať]]></entry>
	<entry key="197"><![CDATA[Uložiť a exportovať]]></entry>
	<entry key="199"><![CDATA[Uložiť ako]]></entry>
	<entry key="200"><![CDATA[Meno súboru]]></entry>
	<entry key="204"><![CDATA[Chyba]]></entry>
	<entry key="213"><![CDATA[Zaslať pozvanie]]></entry>
	<entry key="215"><![CDATA[Predmet]]></entry>
	<entry key="216"><![CDATA[Príjemca]]></entry>
	<entry key="217"><![CDATA[Správa]]></entry>
	<entry key="218"><![CDATA[Poslať]]></entry>
	<entry key="230"><![CDATA[Nahrávanie dát, prosím čakajte]]></entry>
	<entry key="231"><![CDATA[Nesprávne heslo]]></entry>
	<entry key="232"><![CDATA[Zadajte 2 rovnaké heslá]]></entry>
	<entry key="234"><![CDATA[Zadali ste nesprávny email]]></entry>
	<entry key="235"><![CDATA[Registrácia kompletná]]></entry>
	<entry key="239"><![CDATA[Zdieľať/nahrávať plochu]]></entry>
	<entry key="244"><![CDATA[Chat]]></entry>
	<entry key="245"><![CDATA[Súbory]]></entry>
	<entry key="254"><![CDATA[of]]></entry>
	<entry key="256"><![CDATA[Predchádzajúca strana]]></entry>
	<entry key="257"><![CDATA[Ďalšia strana]]></entry>
	<entry key="259"><![CDATA[Zoom --]]></entry>
	<entry key="260"><![CDATA[Zoom ++]]></entry>
	<entry key="263"><![CDATA[Nastavenie]]></entry>
	<entry key="265"><![CDATA[Kľúč]]></entry>
	<entry key="266"><![CDATA[Nastavenie]]></entry>
	<entry key="268"><![CDATA[Posledná zmena]]></entry>
	<entry key="269"><![CDATA[Obnovené]]></entry>
	<entry key="271"><![CDATA[Hodnota]]></entry>
	<entry key="274"><![CDATA[Zmazať používateľa zo spoločnosti]]></entry>
	<entry key="275"><![CDATA[D]]></entry>
	<entry key="277"><![CDATA[Správy]]></entry>
	<entry key="281"><![CDATA[Pomoc a podpora]]></entry>
	<entry key="282"><![CDATA[https://openmeetings.apache.org/]]></entry>
	<entry key="283"><![CDATA[https://openmeetings.apache.org/mailing-lists.html]]></entry>
	<entry key="284"><![CDATA[Nahlásiť chybu]]></entry>
	<entry key="286"><![CDATA[Stránka projektu (https://openmeetings.apache.org)]]></entry>
	<entry key="287"><![CDATA[Zoznam používateľov (https://openmeetings.apache.org/mailing-lists.html)]]></entry>
	<entry key="288"><![CDATA[Zapamätať prihlásenie]]></entry>
	<entry key="290"><![CDATA[My home page]]></entry>
	<entry key="291"><![CDATA[Calendar]]></entry>
	<entry key="306"><![CDATA[Nastavenie mikrofónu a kamery]]></entry>
	<entry key="308"><![CDATA[Východ]]></entry>
	<entry key="309"><![CDATA[Späť k miestnostiam]]></entry>
	<entry key="310"><![CDATA[Odhlásiť]]></entry>
	<entry key="311"><![CDATA[Zabudli ste heslo?]]></entry>
	<entry key="312"><![CDATA[Resetovať heslo]]></entry>
	<entry key="313"><![CDATA[Using email address]]></entry>
	<entry key="314"><![CDATA[Using login]]></entry>
	<entry key="315"><![CDATA[Váš email]]></entry>
	<entry key="316"><![CDATA[Vaše prihlásenie]]></entry>
	<entry key="317"><![CDATA[Poslať email s reštartovacím odkazom]]></entry>
	<entry key="321"><![CDATA[The email containing a special link has been sent to the email address, registered to the user corresponding to the data entered]]></entry>
	<entry key="325"><![CDATA[Resetovať vaše heslo]]></entry>
	<entry key="327"><![CDATA[Zmeniť heslo]]></entry>
	<entry key="328"><![CDATA[Nové heslo]]></entry>
	<entry key="332"><![CDATA[Heslo nastavené. Môžte sa prihlásiť.]]></entry>
	<entry key="348"><![CDATA[Jazykový editor]]></entry>
	<entry key="353"><![CDATA[Field values]]></entry>
	<entry key="360"><![CDATA[Export]]></entry>
	<entry key="362"><![CDATA[Add new language]]></entry>
	<entry key="363"><![CDATA[Delete language]]></entry>
	<entry key="366"><![CDATA[Add language]]></entry>
	<entry key="367"><![CDATA[Backup]]></entry>
	<entry key="376"><![CDATA[Zdravím]]></entry>
	<entry key="377"><![CDATA[Upraviť profil]]></entry>
	<entry key="378"><![CDATA[Nová správa]]></entry>
	<entry key="379"><![CDATA[Nahrať nový obrázok]]></entry>
	<entry key="387"><![CDATA[Importovať]]></entry>
	<entry key="395"><![CDATA[Nahrávky]]></entry>
	<entry key="398"><![CDATA[Používatelia]]></entry>
	<entry key="404"><![CDATA[Kliknite na miestnosť pre informácie o miestnosti]]></entry>
	<entry key="406"><![CDATA[Miestnosť]]></entry>
	<entry key="407"><![CDATA[Používatelia v tejto miestnosti]]></entry>
	<entry key="408"><![CDATA[od]]></entry>
	<entry key="419"><![CDATA[Nahrávanie. Používateľ:]]></entry>
	<entry key="424"><![CDATA[Zmeniť farbu]]></entry>
	<entry key="426"><![CDATA[Znemožniť/umožniť farbu]]></entry>
	<entry key="427"><![CDATA[Zmeniť farbu výplne]]></entry>
	<entry key="428"><![CDATA[Znemožniť/umožniť farbu výplne]]></entry>
	<entry key="429"><![CDATA[Zmeniť širku]]></entry>
	<entry key="433"><![CDATA[Hosť]]></entry>
	<entry key="442"><![CDATA[Delete server chat log]]></entry>
	<entry key="482"><![CDATA[Participujúci]]></entry>
	<entry key="498"><![CDATA[V tejto miestnosti nie je moderátor, ale sú tu participujúci. Musíte požiadať o moderáciu alebo počkať.]]></entry>
	<entry key="500"><![CDATA[{0} - Pozvanie]]></entry>
	<entry key="501"><![CDATA[Správa od:]]></entry>
	<entry key="502"><![CDATA[Správa:]]></entry>
	<entry key="504"><![CDATA[Kliknite sem pre vstup do miestnosti:]]></entry>
	<entry key="505"><![CDATA[Ak máte problém s odkazom, skopírujte ho do vášho prehliadača:]]></entry>
	<entry key="506"><![CDATA[{0} prihláseniep]]></entry>
	<entry key="507"><![CDATA[Your userdata]]></entry>
	<entry key="511"><![CDATA[{0}-Team]]></entry>
	<entry key="512"><![CDATA[{0} prihlásenie]]></entry>
	<entry key="513"><![CDATA[{0} - Reset Password]]></entry>
	<entry key="514"><![CDATA[Kliknite na tento link pre zadanie nového hesla]]></entry>
	<entry key="515"><![CDATA[Kliknite sem pre zadanie nového hesla]]></entry>
	<entry key="517"><![CDATA[{0} Reset hesla]]></entry>
	<entry key="524"><![CDATA[Chránené heslom]]></entry>
	<entry key="526"><![CDATA[Validačná doba]]></entry>
	<entry key="527"><![CDATA[Nekonečné]]></entry>
	<entry key="528"><![CDATA[Obdobie]]></entry>
	<entry key="529"><![CDATA[Jednorázové]]></entry>
	<entry key="530"><![CDATA[Platné od]]></entry>
	<entry key="531"><![CDATA[Platné do]]></entry>
	<entry key="537"><![CDATA[Skontrolovať heslo]]></entry>
	<entry key="545"><![CDATA[x]]></entry>
	<entry key="546"><![CDATA[os x]]></entry>
	<entry key="547"><![CDATA[y]]></entry>
	<entry key="548"><![CDATA[os y]]></entry>
	<entry key="549"><![CDATA[š]]></entry>
	<entry key="551"><![CDATA[v]]></entry>
	<entry key="553"><![CDATA[Zmeniť priehľadnosť]]></entry>
	<entry key="556"><![CDATA[Pripojenie na server zlyhalo]]></entry>
	<entry key="557"><![CDATA[Ukazovátko]]></entry>
	<entry key="565"><![CDATA[Pripomienka]]></entry>
	<entry key="569"><![CDATA[Umiestnenie]]></entry>
	<entry key="572"><![CDATA[Názov]]></entry>
	<entry key="582"><![CDATA[Tabuľa]]></entry>
	<entry key="583"><![CDATA[Pozerať nahrávky stretnutí]]></entry>
	<entry key="586"><![CDATA[Create users, rooms, organisations<br/> and change configuration]]></entry>
	<entry key="593"><![CDATA[Začať nahrávanie]]></entry>
	<entry key="594"><![CDATA[Nahrať a importovať dialóg. Prosím vyberte súbor.]]></entry>
	<entry key="596"><![CDATA[Vybrať súbor]]></entry>
	<entry key="597"><![CDATA[Pripojenia]]></entry>
	<entry key="601"><![CDATA[Pripojený od]]></entry>
	<entry key="602"><![CDATA[Miestnosť / Oblasť]]></entry>
	<entry key="603"><![CDATA[Vyhodiť používateľa]]></entry>
	<entry key="605"><![CDATA[Naozaj chcete vyhodiť tohto klienta z miestnosti?]]></entry>
	<entry key="606"><![CDATA[Vaše stretnutie bolo zavreté administrátorom alebo moderátorom.]]></entry>
	<entry key="607"><![CDATA[Telefón]]></entry>
	<entry key="615"><![CDATA[Tabuľa]]></entry>
	<entry key="619"><![CDATA[Typ miestnosti]]></entry>
	<entry key="620"><![CDATA[Miestnosť]]></entry>
	<entry key="634"><![CDATA[Chcete naozaj odísť?]]></entry>
	<entry key="635"><![CDATA[Akcia]]></entry>
	<entry key="636"><![CDATA[Demo miestnosť]]></entry>
	<entry key="637"><![CDATA[Demo čas]]></entry>
	<entry key="640"><![CDATA[Moderované]]></entry>
	<entry key="641"><![CDATA[Prosím počkajte na vstup moderátora do miestnosti]]></entry>
	<entry key="667"><![CDATA[Pre dokončenie registrácie kliknite na nasledujúci odkaz]]></entry>
	<entry key="668"><![CDATA[Kliknite pre overenie vášho emailu]]></entry>
	<entry key="677"><![CDATA[Používateľ]]></entry>
	<entry key="678"><![CDATA[Prístup k tabuli]]></entry>
	<entry key="679"><![CDATA[Moderátor]]></entry>
	<entry key="692"><![CDATA[Používateľ]]></entry>
	<entry key="696"><![CDATA[Musíte počkať pokiaľ moderátor vstúpi do miestnosti]]></entry>
	<entry key="702"><![CDATA[Nahrať súbor]]></entry>
	<entry key="703"><![CDATA[Pridať súbor]]></entry>
	<entry key="705"><![CDATA[Kôš]]></entry>
	<entry key="706"><![CDATA[Moje súbory]]></entry>
	<entry key="707"><![CDATA[Súbory v miestnosti(verejné)]]></entry>
	<entry key="711"><![CDATA[Zmeniť meno]]></entry>
	<entry key="712"><![CDATA[Nový priečinok]]></entry>
	<entry key="713"><![CDATA[Naozaj chcete zmazať túto položku?]]></entry>
	<entry key="714"><![CDATA[Hľadať]]></entry>
	<entry key="730"><![CDATA[Zdieľač plochy]]></entry>
	<entry key="732"><![CDATA[Začať zdieľanie]]></entry>
	<entry key="733"><![CDATA[Pauza]]></entry>
	<entry key="734"><![CDATA[Vyberte plochu zdieľania:]]></entry>
	<entry key="740"><![CDATA[Šírka]]></entry>
	<entry key="741"><![CDATA[Výška]]></entry>
	<entry key="753"><![CDATA[Obnoviť]]></entry>
	<entry key="758"><![CDATA[Otestovať audio alebo video nastavenie pred vstupom do miestnosti môžte nahratím stretnutia na pár sekúnd. Môžte si potom prehrať nahrávku a skontrolovať svoje audio/video.]]></entry>
	<entry key="764"><![CDATA[PLAY]]></entry>
	<entry key="765"><![CDATA[Môžte prejsť bez testovania ak neplánujete zverejniť svoje audio/video.]]></entry>
	<entry key="767"><![CDATA[Level-meter]]></entry>
	<entry key="768"><![CDATA[Stlačte štart]]></entry>
	<entry key="771"><![CDATA[Vybrať miestnosť]]></entry>
	<entry key="772"><![CDATA[Skontrolovať nastavenie]]></entry>
	<entry key="773"><![CDATA[Začať konferenciu]]></entry>
	<entry key="775"><![CDATA[Začať nahrávanie]]></entry>
	<entry key="777"><![CDATA[Verejné miestnosti]]></entry>
	<entry key="778"><![CDATA[Verejné miestnosti sú prístupné pre všetkých používateľov]]></entry>
	<entry key="779"><![CDATA[Súkromné miestnosti]]></entry>
	<entry key="780"><![CDATA[Súkromné miestnosti sú prístupné len pr používateľov určitej spoločnosti.]]></entry>
	<entry key="781"><![CDATA[Moje miestnosti]]></entry>
	<entry key="782"><![CDATA[Rooms in this section are created for personal usage. There are some standard rooms plus the ones that are created through the calendar and have a start and an end date. The rooms created via the calendar are only listed in this section as long as they are valid.]]></entry>
	<entry key="784"><![CDATA[Požiadať o moderáciu]]></entry>
	<entry key="785"><![CDATA[Požiadať o prístup k tabuli]]></entry>
	<entry key="786"><![CDATA[Požiadať o audio/video prístup]]></entry>
	<entry key="792"><![CDATA[Miestnosti]]></entry>
	<entry key="797"><![CDATA[Warning]]></entry>
	<entry key="799"><![CDATA[Day]]></entry>
	<entry key="800"><![CDATA[Week]]></entry>
	<entry key="801"><![CDATA[Month]]></entry>
	<entry key="803"><![CDATA[Attendees]]></entry>
	<entry key="815"><![CDATA[Event details]]></entry>
	<entry key="816"><![CDATA[Default moderators]]></entry>
	<entry key="817"><![CDATA[Super]]></entry>
	<entry key="823"><![CDATA[If the room is moderated, any users with a moderator or administrator level access are automatically set to moderator when they enter the room]]></entry>
	<entry key="828"><![CDATA[If you add an organisation to the room only users of that organisation have access to it]]></entry>
	<entry key="830"><![CDATA[Limitations]]></entry>
	<entry key="832"><![CDATA[Ste si istý?]]></entry>
	<entry key="833"><![CDATA[Naozaj chcete zmazať túto položku?]]></entry>
	<entry key="843"><![CDATA[Tool Properties]]></entry>
	<entry key="848"><![CDATA[Vidieť plochu]]></entry>
	<entry key="850"><![CDATA[chce zdieľať svoju plochu. Zobraziť?]]></entry>
	<entry key="860"><![CDATA[Moje nahrávky]]></entry>
	<entry key="861"><![CDATA[Verejné nahrávky]]></entry>
	<entry key="864"><![CDATA[Dĺžka]]></entry>
	<entry key="865"><![CDATA[Dátum]]></entry>
	<entry key="867"><![CDATA[Stiahnuť]]></entry>
	<entry key="871"><![CDATA[Začať nahrávanie]]></entry>
	<entry key="872"><![CDATA[Ukončiť nahrávanie]]></entry>
	<entry key="879"><![CDATA[Povoliť používateľovi otázky]]></entry>
	<entry key="880"><![CDATA[Vypnúť - aby vás používatelia nevyrušovali]]></entry>
	<entry key="881"><![CDATA[Práva]]></entry>
	<entry key="887"><![CDATA[Nastala chyba počas nahrávania]]></entry>
	<entry key="888"><![CDATA[Nahrávka nie je ešte hotová na prezeranie]]></entry>
	<entry key="923"><![CDATA[Home drive size]]></entry>
	<entry key="924"><![CDATA[Public drive size]]></entry>
	<entry key="996"><![CDATA[Status]]></entry>
	<entry key="1001"><![CDATA[SIP-Settings]]></entry>
	<entry key="1002"><![CDATA[The Conference Number and PIN is automatically created via the OpenXG RPC-Gateway]]></entry>
	<entry key="1003"><![CDATA[SIP Number]]></entry>
	<entry key="1004"><![CDATA[PIN]]></entry>
	<entry key="1005"><![CDATA[Zmazať všetky objekty na tomto slide iba!]]></entry>
	<entry key="1076"><![CDATA[Audio only room]]></entry>
	<entry key="1077"><![CDATA[Turn this Flag on and the users will have only the Audio-Option and no Video in a conference room. This can by good to save bandwidth.]]></entry>
	<entry key="1089"><![CDATA[Quality of the ScreenShare:]]></entry>
	<entry key="1098"><![CDATA[The webinar is already closed, you will be redirected to some interesting offerings in]]></entry>
	<entry key="1099"><![CDATA[Close Room]]></entry>
	<entry key="1100"><![CDATA[Exit URL]]></entry>
	<entry key="1101"><![CDATA[Room termination settings]]></entry>
	<entry key="1102"><![CDATA[If the room is closed users will be redirected to the exit URL.]]></entry>
	<entry key="1103"><![CDATA[Ldap]]></entry>
	<entry key="1106"><![CDATA[Config File]]></entry>
	<entry key="1107"><![CDATA[Ldap Config]]></entry>
	<entry key="1109"><![CDATA[Enabled]]></entry>
	<entry key="1110"><![CDATA[Inserted]]></entry>
	<entry key="1111"><![CDATA[Inserted by]]></entry>
	<entry key="1112"><![CDATA[Updated]]></entry>
	<entry key="1114"><![CDATA[The config files are in the folder OM_DATA_FOLDER/conf. You need to manually upload the files to this folder. Changes to the config file are immediately online.]]></entry>
	<entry key="1115"><![CDATA[Config file name]]></entry>
	<entry key="1116"><![CDATA[If you enable "Add Domain to username" the value of the field "domain" is added to each login that the user enters in the login box. This is useful if the Login in the Ldap is stored including the domain name. Example: User enters "hans" domain is specified as "localhost.com", login that is verified against Ldap is: hans@localhost.com]]></entry>
	<entry key="1117"><![CDATA[Add Domain to username]]></entry>
	<entry key="1118"><![CDATA[Domain]]></entry>
	<entry key="1121"><![CDATA[Remote clipboard text]]></entry>
	<entry key="1131"><![CDATA[Invite user to conference room]]></entry>
	<entry key="1132"><![CDATA[Choose a conference room. The invited user will get a message with your name and a link to the room.]]></entry>
	<entry key="1134"><![CDATA[Enter room after sending invitation]]></entry>
	<entry key="1135"><![CDATA[Invite]]></entry>
	<entry key="1137"><![CDATA[would like to invite you to the conference room:]]></entry>
	<entry key="1138"><![CDATA[Invite message]]></entry>
	<entry key="1143"><![CDATA[Timezone]]></entry>
	<entry key="1147"><![CDATA[Created by]]></entry>
	<entry key="1151"><![CDATA[New {0} conference:]]></entry>
	<entry key="1152"><![CDATA[Details:]]></entry>
	<entry key="1155"><![CDATA[Changed {0} conference:]]></entry>
	<entry key="1156"><![CDATA[Organizer:]]></entry>
	<entry key="1157"><![CDATA[Canceled {0} conference:]]></entry>
	<entry key="1158"><![CDATA[{0} conference Reminder:]]></entry>
	<entry key="1159"><![CDATA[Community settings]]></entry>
	<entry key="1160"><![CDATA[Show contact data to everybody]]></entry>
	<entry key="1162"><![CDATA[My offerings]]></entry>
	<entry key="1163"><![CDATA[My interests]]></entry>
	<entry key="1166"><![CDATA[Fields of interest]]></entry>
	<entry key="1167"><![CDATA[Contact information]]></entry>
	<entry key="1168"><![CDATA[Show contact data to contacts only]]></entry>
	<entry key="1169"><![CDATA[Show contact data to nobody]]></entry>
	<entry key="1170"><![CDATA[My Profile]]></entry>
	<entry key="1172"><![CDATA[Search users]]></entry>
	<entry key="1177"><![CDATA[User offers]]></entry>
	<entry key="1178"><![CDATA[User looks for]]></entry>
	<entry key="1179"><![CDATA[Freetext]]></entry>
	<entry key="1182"><![CDATA[Offers]]></entry>
	<entry key="1183"><![CDATA[Searchs]]></entry>
	<entry key="1184"><![CDATA[Searchresult]]></entry>
	<entry key="1186"><![CDATA[Add to contacts]]></entry>
	<entry key="1188"><![CDATA[Contacts and Messages]]></entry>
	<entry key="1189"><![CDATA[Pending contacts]]></entry>
	<entry key="1190"><![CDATA[Accept]]></entry>
	<entry key="1191"><![CDATA[Deny]]></entry>
	<entry key="1192"><![CDATA[Hi,]]></entry>
	<entry key="1193"><![CDATA[would like to add you as contact.]]></entry>
	<entry key="1194"><![CDATA[Check your contact requests in {0} or click on those links to accept or deny the request]]></entry>
	<entry key="1196"><![CDATA[Your contact list]]></entry>
	<entry key="1198"><![CDATA[confirmed you as contact!]]></entry>
	<entry key="1202"><![CDATA[From]]></entry>
	<entry key="1206"><![CDATA[Messages]]></entry>
	<entry key="1207"><![CDATA[New Mail]]></entry>
	<entry key="1208"><![CDATA[Click to write a new message to any of your contacts]]></entry>
	<entry key="1209"><![CDATA[Write new message]]></entry>
	<entry key="1210"><![CDATA[To:]]></entry>
	<entry key="1211"><![CDATA[Subject:]]></entry>
	<entry key="1218"><![CDATA[Book conference room]]></entry>
	<entry key="1221"><![CDATA[Add an optional request for meeting to the message and create a conference room. The Event is then copied in the calendar of every participant.]]></entry>
	<entry key="1222"><![CDATA[Inbox]]></entry>
	<entry key="1223"><![CDATA[Sent]]></entry>
	<entry key="1224"><![CDATA[Trash]]></entry>
	<entry key="1234"><![CDATA[Delete contact from list]]></entry>
	<entry key="1235"><![CDATA[User Profile]]></entry>
	<entry key="1236"><![CDATA[Show user profile]]></entry>
	<entry key="1239"><![CDATA[Select all]]></entry>
	<entry key="1240"><![CDATA[Select none]]></entry>
	<entry key="1241"><![CDATA[Select unread]]></entry>
	<entry key="1242"><![CDATA[Select read]]></entry>
	<entry key="1243"><![CDATA[Move to folder ...]]></entry>
	<entry key="1247"><![CDATA[Mark unread]]></entry>
	<entry key="1248"><![CDATA[Mark read]]></entry>
	<entry key="1252"><![CDATA[Actions ...]]></entry>
	<entry key="1253"><![CDATA[Send private message]]></entry>
	<entry key="1255"><![CDATA[Move to Inbox]]></entry>
	<entry key="1256"><![CDATA[Delete (final)]]></entry>
	<entry key="1259"><![CDATA[Add folders and organize your messages!]]></entry>
	<entry key="1261"><![CDATA[Add]]></entry>
	<entry key="1262"><![CDATA[Delete folder]]></entry>
	<entry key="1268"><![CDATA[The user does not share personal contact data.]]></entry>
	<entry key="1269"><![CDATA[The user shares their personal contact data only to contacts.]]></entry>
	<entry key="1287"><![CDATA[Choose your nickname]]></entry>
	<entry key="1296"><![CDATA[Member since]]></entry>
	<entry key="1301"><![CDATA[New private message:]]></entry>
	<entry key="1302"><![CDATA[Click here to visit your profile to see the full message ...]]></entry>
	<entry key="1308"><![CDATA[Owner Id]]></entry>
	<entry key="1312"><![CDATA[Do directly load to whiteboard]]></entry>
	<entry key="1313"><![CDATA[Do you really want to remove this whiteboard? This action cannot be undone.]]></entry>
	<entry key="1315"><![CDATA[Do not forget start recording! One user per room always needs to start it to have the recording afterwards.]]></entry>
	<entry key="1316"><![CDATA[Start Recording]]></entry>
	<entry key="1323"><![CDATA[Clip arts]]></entry>
	<entry key="1340"><![CDATA[Do you really want to delete the complete content on the whiteboard?]]></entry>
	<entry key="1355"><![CDATA[Allow recording]]></entry>
	<entry key="1356"><![CDATA[Wait for recording]]></entry>
	<entry key="1359"><![CDATA[Do you really want to delete the content on the current slide?]]></entry>
	<entry key="1360"><![CDATA[Accept and grant user right]]></entry>
	<entry key="1361"><![CDATA[Deny]]></entry>
	<entry key="1362"><![CDATA[I]]></entry>
	<entry key="1363"><![CDATA[Activities and actions]]></entry>
	<entry key="1410"><![CDATA[Poll Name]]></entry>
	<entry key="1411"><![CDATA[You]]></entry>
	<entry key="1412"><![CDATA[Archieved Polls]]></entry>
	<entry key="1413"><![CDATA[active]]></entry>
	<entry key="1414"><![CDATA[Simple Chart]]></entry>
	<entry key="1415"><![CDATA[Pie Chart]]></entry>
	<entry key="1418"><![CDATA[Close Poll]]></entry>
	<entry key="1419"><![CDATA[Are you sure you want to close this Poll? No one will be able to vote]]></entry>
	<entry key="1420"><![CDATA[Delete Poll]]></entry>
	<entry key="1421"><![CDATA[Are you sure you want to delete this Poll? The results will be deleted as well.]]></entry>
	<entry key="1422"><![CDATA[Language ISO Code]]></entry>
	<entry key="1429"><![CDATA[Cam resolution]]></entry>
	<entry key="1430"><![CDATA[Changing the resolution affects bandwidth, bigger picture needs more bandwith!]]></entry>
	<entry key="1443"><![CDATA[Layout options]]></entry>
	<entry key="1444"><![CDATA[New Event]]></entry>
	<entry key="1445"><![CDATA[Password protected are the links to the conference that are send to the participents when you save the calendar event, not the room! That means if you save the event multiple times but with different passwords every participent receives a new link that has a different password. But old links still work once send!]]></entry>
	<entry key="1447"><![CDATA[Show sip dialer]]></entry>
	<entry key="1448"><![CDATA[Call]]></entry>
	<entry key="1450"><![CDATA[Your home!]]></entry>
	<entry key="1451"><![CDATA[Plan your meetings]]></entry>
	<entry key="1452"><![CDATA[Watch recordings and interviews]]></entry>
	<entry key="1454"><![CDATA[Manage users and rights]]></entry>
	<entry key="1455"><![CDATA[Manage connections and kick users]]></entry>
	<entry key="1456"><![CDATA[Manage usergroups]]></entry>
	<entry key="1457"><![CDATA[Manage conference rooms]]></entry>
	<entry key="1458"><![CDATA[Manage system settings]]></entry>
	<entry key="1459"><![CDATA[Manage labels and wording]]></entry>
	<entry key="1460"><![CDATA[Manage LDAP and ADS configurations]]></entry>
	<entry key="1461"><![CDATA[Export/Import System Backups]]></entry>
	<entry key="1479"><![CDATA[Upload new file to file explorer]]></entry>
	<entry key="1480"><![CDATA[Open new dialog with sharing settings]]></entry>
	<entry key="1481"><![CDATA[An existing moderator must approve it]]></entry>
	<entry key="1482"><![CDATA[Ask moderator to share your webcam/microphone]]></entry>
	<entry key="1483"><![CDATA[Gather feedback by creating a poll]]></entry>
	<entry key="1484"><![CDATA[Past and current poll results as charts]]></entry>
	<entry key="1485"><![CDATA[Vote if there is a poll for this conference room]]></entry>
	<entry key="1488"><![CDATA[Call external people via VoIP/SIP]]></entry>
	<entry key="1489"><![CDATA[Send an email with a direct link to this room]]></entry>
	<entry key="1492"><![CDATA[Ask moderator to share your whiteboard]]></entry>
	<entry key="1493"><![CDATA[Start Private Chat]]></entry>
	<entry key="1494"><![CDATA[All]]></entry>
	<entry key="1500"><![CDATA[Server Name]]></entry>
	<entry key="1504"><![CDATA[Publishing. User:]]></entry>
	<entry key="1506"><![CDATA[Rooms common to all users]]></entry>
	<entry key="1507"><![CDATA[Rooms common to the current user group]]></entry>
	<entry key="1508"><![CDATA[Rooms of the current user]]></entry>
	<entry key="1509"><![CDATA[Create/Modify appointment special room]]></entry>
	<entry key="1513"><![CDATA[Is chat moderated]]></entry>
	<entry key="1515"><![CDATA[Chat panel opened by default]]></entry>
	<entry key="1516"><![CDATA[Files panel opened by default]]></entry>
	<entry key="1526"><![CDATA[Generate URL]]></entry>
	<entry key="1527"><![CDATA[Network testing]]></entry>
	<entry key="1538"><![CDATA[Enable SIP transport in the room]]></entry>
	<entry key="1546"><![CDATA[Welcome]]></entry>
	<entry key="1547"><![CDATA[Widget displaying basic user info and support links]]></entry>
	<entry key="1548"><![CDATA[Widgets]]></entry>
	<entry key="1549"><![CDATA[About]]></entry>
	<entry key="1551"><![CDATA[Version]]></entry>
	<entry key="1552"><![CDATA[Revision]]></entry>
	<entry key="1553"><![CDATA[Build date]]></entry>
	<entry key="1555"><![CDATA[today]]></entry>
	<entry key="1556"><![CDATA[Jan]]></entry>
	<entry key="1557"><![CDATA[Feb]]></entry>
	<entry key="1558"><![CDATA[Mar]]></entry>
	<entry key="1559"><![CDATA[Apr]]></entry>
	<entry key="1560"><![CDATA[May]]></entry>
	<entry key="1561"><![CDATA[Jun]]></entry>
	<entry key="1562"><![CDATA[Jul]]></entry>
	<entry key="1563"><![CDATA[Aug]]></entry>
	<entry key="1564"><![CDATA[Sep]]></entry>
	<entry key="1565"><![CDATA[Oct]]></entry>
	<entry key="1566"><![CDATA[Nov]]></entry>
	<entry key="1567"><![CDATA[Dec]]></entry>
	<entry key="1571"><![CDATA[OAuth2]]></entry>
	<entry key="1572"><![CDATA[Manage OAuth2 configurations]]></entry>
	<entry key="1575"><![CDATA[Icon URL]]></entry>
	<entry key="1578"><![CDATA[Request key URL]]></entry>
	<entry key="1579"><![CDATA[Request token URL]]></entry>
	<entry key="1580"><![CDATA[Request info URL]]></entry>
	<entry key="1581"><![CDATA[OAuth2 config]]></entry>
	<entry key="1586"><![CDATA[Request token attributes]]></entry>
	<entry key="1587"><![CDATA[Redirect uri]]></entry>
	<entry key="1588"><![CDATA[You can enter email address in the format: firstname1 lastname1 <email1> or "firstname2 lastname2" <email2> or 'firstname3 lastname3' <email3> or email]]></entry>
	<entry key="1590"><![CDATA[Display]]></entry>
	<entry key="1592"><![CDATA[End date entered is earlier than start date.]]></entry>
	<entry key="1593"><![CDATA[Exit value]]></entry>
	<entry key="1594"><![CDATA[Conversion messages]]></entry>
	<entry key="1595"><![CDATA[Recording file is not found]]></entry>
	<entry key="1599"><![CDATA[Access denied. You have no rights to enter this room.]]></entry>
	<entry key="1600"><![CDATA[Re-convert]]></entry>
	<entry key="access.denied.header"><![CDATA[Access denied. You are not authorized to perform this action.]]></entry>
	<entry key="account.created"><![CDATA[Vaše konto bolo vytvorené. Môžte sa prihlásiť.]]></entry>
	<entry key="activities.ask.question"><![CDATA[would like to ask a question]]></entry>
	<entry key="activities.autoclean"><![CDATA[Auto-clean]]></entry>
	<entry key="activities.msg.enter"><![CDATA[enter the room.]]></entry>
	<entry key="activities.msg.exit"><![CDATA[has left the room.]]></entry>
	<entry key="activities.request.right.audio"><![CDATA[requests permission to turn on micropone]]></entry>
	<entry key="activities.request.right.moderator"><![CDATA[requests permission to be moderator]]></entry>
	<entry key="activities.request.right.muteothers"><![CDATA[requests permission to mute others]]></entry>
	<entry key="activities.request.right.presenter"><![CDATA[requests permission to be presenter]]></entry>
	<entry key="activities.request.right.remote"><![CDATA[requests permission to control screen during screen sharing]]></entry>
	<entry key="activities.request.right.share"><![CDATA[requests permission to share/record screen]]></entry>
	<entry key="activities.request.right.video"><![CDATA[requests permission to turn on camera]]></entry>
	<entry key="activities.request.right.wb"><![CDATA[requests permission to draw on the whiteboard]]></entry>
	<entry key="admin.backup.add.files"><![CDATA[Include uploaded files and recordings in backup]]></entry>
	<entry key="admin.backup.cmd.line.desc"><![CDATA[To save time and internet traffic you can use command line admin to backup/restore/upgrade: <ol> <li>go to OM install dir (for ex. /opt/om)</li> <li>stop OM (for ex. ./bin/shutdown.sh)</li> <li>./admin.sh -b -file ~/today_om_backup.zip (create backup of current OM)</li> <li>download archive with new OM</li> <li>mv /opt/om /opt/om.bak (move working version of OM just in case :))</li> <li>extract downloaded OM to the /opt/om</li> <li>./admin.sh -i -file ~/today_om_backup.zip (or './admin.sh -i -file ~/today_om_backup.zip --db-type mysql --db-user om_user --db-pass om_user_pass' in case of you are using non-default DB )</li> <li>start OM</li> </ol>]]></entry>
	<entry key="admin.backup.import.lbl"><![CDATA[System import]]></entry>
	<entry key="admin.backup.lbl"><![CDATA[System backup]]></entry>
	<entry key="admin.backup.steps"><![CDATA[The backup includes are user generated data and configuration.<br/>
To update your system,
<ol>
  <li>** Do DB backup, OM folder backup</li>
  <li>export your old system</li>
  <li>drop database</li>
  <li>re-install the new package into a new database</li>
  <li>and import the backup file again</li>
  <li>The backup should be imported before your users will have access to the system</li>
</ol>]]></entry>
	<entry key="admin.email.body"><![CDATA[Body]]></entry>
	<entry key="admin.email.errorCount"><![CDATA[Error Count]]></entry>
	<entry key="admin.email.group.label"><![CDATA[Email message]]></entry>
	<entry key="admin.email.lastError"><![CDATA[Last Error]]></entry>
	<entry key="admin.email.recipients"><![CDATA[Recipients]]></entry>
	<entry key="admin.email.reset.status"><![CDATA[Reset Status]]></entry>
	<entry key="admin.email.status.DONE"><![CDATA[Done]]></entry>
	<entry key="admin.email.status.ERROR"><![CDATA[Error]]></entry>
	<entry key="admin.email.status.NONE"><![CDATA[None]]></entry>
	<entry key="admin.email.status.SENDING"><![CDATA[Sending]]></entry>
	<entry key="admin.extra.group.label"><![CDATA[URL details]]></entry>
	<entry key="admin.extra.link"><![CDATA[URL]]></entry>
	<entry key="admin.group.form.days"><![CDATA[days]]></entry>
	<entry key="admin.group.form.limited"><![CDATA[Limits enabled]]></entry>
	<entry key="admin.group.form.logo"><![CDATA[Logo]]></entry>
	<entry key="admin.group.form.maxFilesSize"><![CDATA[Maximum files size]]></entry>
	<entry key="admin.group.form.maxRecordingsSize"><![CDATA[Maximum recordings size]]></entry>
	<entry key="admin.group.form.maxRooms"><![CDATA[Maximum room number]]></entry>
	<entry key="admin.group.form.minutes"><![CDATA[minutes]]></entry>
	<entry key="admin.group.form.recordingTtl"><![CDATA[Recordings expire in]]></entry>
	<entry key="admin.group.form.reminderDays"><![CDATA[Expire reminder sent in]]></entry>
	<entry key="admin.group.form.tag"><![CDATA[Tag]]></entry>
	<entry key="admin.group.new.users.notification.interval"><![CDATA[New user notification interval]]></entry>
	<entry key="admin.oauth.attr.oauth"><![CDATA[OAuth User attribute]]></entry>
	<entry key="admin.oauth.attr.om"><![CDATA[OM User attribute]]></entry>
	<entry key="admin.oauth.req.info.method"><![CDATA[Request info method]]></entry>
	<entry key="admin.oauth.req.token.method"><![CDATA[Request token method]]></entry>
	<entry key="admin.oauth.user.mapping"><![CDATA[User mapping]]></entry>
	<entry key="admin.purge"><![CDATA[Purge]]></entry>
	<entry key="admin.purge.desc"><![CDATA[Do you really want to purge this item? This can't be undone!]]></entry>
	<entry key="admin.restore"><![CDATA[Restore]]></entry>
	<entry key="admin.room.hidden.elements"><![CDATA[Hidden room elements]]></entry>
	<entry key="admin.room.wait-moderator.info"><![CDATA[No one can use the room until moderator has joined]]></entry>
	<entry key="admin.room.wait-moderator.label"><![CDATA[Wait for a moderator]]></entry>
	<entry key="appointment.reminder.EMAIL"><![CDATA[simple email]]></entry>
	<entry key="appointment.reminder.ICAL"><![CDATA[iCal email]]></entry>
	<entry key="appointment.reminder.NONE"><![CDATA[do not send notification]]></entry>
	<entry key="appointment.tab.advanced"><![CDATA[Advanced]]></entry>
	<entry key="bad.captcha.text"><![CDATA[You have entered incorrect captcha text]]></entry>
	<entry key="bad.password.digit"><![CDATA['Weak' password: at least 1 digit is required]]></entry>
	<entry key="bad.password.lower"><![CDATA['Weak' password: at least 1 lower-case letter is required]]></entry>
	<entry key="bad.password.short"><![CDATA['Weak' password: minimum password length is ${0}]]></entry>
	<entry key="bad.password.special"><![CDATA['Weak' password: at least 1 special symbol '!@#$%^&*][' is required]]></entry>
	<entry key="bad.password.stop"><![CDATA['Weak' password: it shouldn't contain part of the user's email address or username]]></entry>
	<entry key="bad.password.upper"><![CDATA['Weak' password: at least 1 upper-case letter is required]]></entry>
	<entry key="button.label.share"><![CDATA[Share]]></entry>
	<entry key="calendar.addCalendar"><![CDATA[Add External Calendar]]></entry>
	<entry key="calendar.defaultTitle"><![CDATA[New Calendar]]></entry>
	<entry key="calendar.dialogTitle"><![CDATA[Calendar Details]]></entry>
	<entry key="calendar.error"><![CDATA[Error in making connection on the URL specified.]]></entry>
	<entry key="calendar.gcal"><![CDATA[Google Calendar]]></entry>
	<entry key="calendar.googleID"><![CDATA[Google Calendar ID]]></entry>
	<entry key="calendar.googleKey"><![CDATA[Google Calendar API key]]></entry>
	<entry key="calendar.sync"><![CDATA[Sync]]></entry>
	<entry key="calendar.url"><![CDATA[External CalDAV Calendar URL]]></entry>
	<entry key="camera.off"><![CDATA[Camera is off. Click to turn on.]]></entry>
	<entry key="camera.on"><![CDATA[Camera is on. Click to turn off.]]></entry>
	<entry key="captcha.text"><![CDATA[Captcha text]]></entry>
	<entry key="close.settings.tab"><![CDATA[After saving your audio and video settings you may close this browser tab.]]></entry>
	<entry key="convert.errors.file"><![CDATA[There were errors while processing the file]]></entry>
	<entry key="convert.errors.file.missing"><![CDATA[File is not found]]></entry>
	<entry key="current.password"><![CDATA[Current password]]></entry>
	<entry key="dashboard.widget.admin.cleanup.backup"><![CDATA[backup:]]></entry>
	<entry key="dashboard.widget.admin.cleanup.cleanup"><![CDATA[Cleanup]]></entry>
	<entry key="dashboard.widget.admin.cleanup.deleted"><![CDATA[deleted:]]></entry>
	<entry key="dashboard.widget.admin.cleanup.error"><![CDATA[Unexpected error while performing cleanup]]></entry>
	<entry key="dashboard.widget.admin.cleanup.files"><![CDATA[files:]]></entry>
	<entry key="dashboard.widget.admin.cleanup.final"><![CDATA[final:]]></entry>
	<entry key="dashboard.widget.admin.cleanup.import"><![CDATA[import:]]></entry>
	<entry key="dashboard.widget.admin.cleanup.invalid"><![CDATA[invalid:]]></entry>
	<entry key="dashboard.widget.admin.cleanup.missing"><![CDATA[missing count:]]></entry>
	<entry key="dashboard.widget.admin.cleanup.profiles"><![CDATA[profiles:]]></entry>
	<entry key="dashboard.widget.admin.cleanup.show"><![CDATA[Show cleanup report]]></entry>
	<entry key="dashboard.widget.admin.cleanup.streams"><![CDATA[Streams folder:]]></entry>
	<entry key="dashboard.widget.admin.cleanup.title"><![CDATA[Cleanup report]]></entry>
	<entry key="dashboard.widget.admin.cleanup.upload"><![CDATA[Upload folder:]]></entry>
	<entry key="dashboard.widget.admin.cleanup.warn"><![CDATA[Are you sure you want to delete all temporary files? This operation cannot be undone.]]></entry>
	<entry key="dashboard.widget.admin.desc"><![CDATA[General Admin functions]]></entry>
	<entry key="dashboard.widget.admin.title"><![CDATA[Admin functions]]></entry>
	<entry key="dont.ask.again"><![CDATA[Nepýtať sa ma znova]]></entry>
	<entry key="download.pdf"><![CDATA[Stiahnúť ako PDF]]></entry>
	<entry key="download.png"><![CDATA[Stiahnúť ako PNG]]></entry>
	<entry key="edit.settings"><![CDATA[Edit settings]]></entry>
	<entry key="error.bad.credentials"><![CDATA[Username/email and/or password are incorrect.]]></entry>
	<entry key="error.bad.password"><![CDATA[Neplatné heslo]]></entry>
	<entry key="error.cfg.exist"><![CDATA[Configuration with given key already exists, please specify another key or edit existent configuration]]></entry>
	<entry key="error.contact.added"><![CDATA[This user is already in your contact list or has received an invitation to your contact list that is not answered yet.]]></entry>
	<entry key="error.contact.approved"><![CDATA[The user is already approved.]]></entry>
	<entry key="error.contact.denied"><![CDATA[The user is already denied.]]></entry>
	<entry key="error.email.inuse"><![CDATA[Email už je zaregistrovaný]]></entry>
	<entry key="error.hash.invalid"><![CDATA[Pozývací kód je neplatný]]></entry>
	<entry key="error.hash.period"><![CDATA[You invitation code is not valid, the code is only valid during this specific date and time:]]></entry>
	<entry key="error.hash.used"><![CDATA[Toto pozvanie už bolo použité]]></entry>
	<entry key="error.login.inuse"><![CDATA[Používateľské meno už existuje]]></entry>
	<entry key="error.nogroup"><![CDATA[User is not assigned to group.]]></entry>
	<entry key="error.notactivated"><![CDATA[Your account is not activated. Please use the link in the email you received during registration.]]></entry>
	<entry key="error.notallowed"><![CDATA[Autorízácia administrátorom sa vyžaduje]]></entry>
	<entry key="error.reg.disabled"><![CDATA[Registrácia nemožná]]></entry>
	<entry key="error.short.login"><![CDATA[Login is too short]]></entry>
	<entry key="error.type.error"><![CDATA[Chyba]]></entry>
	<entry key="error.type.info"><![CDATA[Správa]]></entry>
	<entry key="error.unknown"><![CDATA[Chyba. Kontaktujte administrátora.]]></entry>
	<entry key="file.name.interview"><![CDATA[Interview]]></entry>
	<entry key="file.name.recording"><![CDATA[Recording]]></entry>
	<entry key="files.download.jpg"><![CDATA[JPG]]></entry>
	<entry key="files.download.original"><![CDATA[Original]]></entry>
	<entry key="files.download.pdf"><![CDATA[PDF]]></entry>
	<entry key="files.root.group"><![CDATA[Group files]]></entry>
	<entry key="find.user"><![CDATA[Find user]]></entry>
	<entry key="fixed.video.pod.size"><![CDATA[Fixed video pod size]]></entry>
	<entry key="form.max.upload.size"><![CDATA[Max upload size]]></entry>
	<entry key="goto.first"><![CDATA[prvý]]></entry>
	<entry key="goto.last"><![CDATA[posledný]]></entry>
	<entry key="goto.next"><![CDATA[ďalší]]></entry>
	<entry key="goto.prev"><![CDATA[predchádzajúci]]></entry>
	<entry key="install.room.conference.micro"><![CDATA[Conference room with microphone option set]]></entry>
	<entry key="install.room.presentation.micro"><![CDATA[Presentation room with microphone option set]]></entry>
	<entry key="install.room.private.conference"><![CDATA[Private Conference Room]]></entry>
	<entry key="install.room.public.conference"><![CDATA[Public Conference Room]]></entry>
	<entry key="install.room.public.interview"><![CDATA[Public Interview Room]]></entry>
	<entry key="install.room.public.presentation"><![CDATA[Public Presentation Room]]></entry>
	<entry key="install.room.public.video.only"><![CDATA[Public Video Only Room]]></entry>
	<entry key="install.room.public.video.wb"><![CDATA[Public Video And Whiteboard Room]]></entry>
	<entry key="install.wizard.congrats.commercial"><![CDATA[There are some companies that offer commercial support for Apache OpenMeetings:]]></entry>
	<entry key="install.wizard.congrats.enter"><![CDATA[Enter the Application]]></entry>
	<entry key="install.wizard.congrats.mail"><![CDATA[Mailing list]]></entry>
	<entry key="install.wizard.congrats.restart"><![CDATA[Database was changed, please restart application to avoid possible issues]]></entry>
	<entry key="install.wizard.db.step.check"><![CDATA[Check]]></entry>
	<entry key="install.wizard.db.step.db2.name"><![CDATA[IBM DB2]]></entry>
	<entry key="install.wizard.db.step.dbname"><![CDATA[Specify the name of the database]]></entry>
	<entry key="install.wizard.db.step.dbtype"><![CDATA[Choose DB type]]></entry>
	<entry key="install.wizard.db.step.error.patch"><![CDATA[Unexpected error while patching persistence file: {0}]]></entry>
	<entry key="install.wizard.db.step.errorprops"><![CDATA[Unable to get the properties]]></entry>
	<entry key="install.wizard.db.step.field.title"><![CDATA[DB configuration]]></entry>
	<entry key="install.wizard.db.step.h2.name"><![CDATA[H2]]></entry>
	<entry key="install.wizard.db.step.host"><![CDATA[Specify DB host]]></entry>
	<entry key="install.wizard.db.step.instructions.db2"><![CDATA[<a target="_blank" href="https://openmeetings.apache.org/IBMDB2Config.html">IBM DB2</a>]]></entry>
	<entry key="install.wizard.db.step.instructions.h2"><![CDATA[<a target="_blank" href="https://openmeetings.apache.org/H2Config.html">H2</a>]]></entry>
	<entry key="install.wizard.db.step.instructions.mssql"><![CDATA[<a target="_blank" href="https://openmeetings.apache.org/MSSQLConfig.html">MSSQL</a>]]></entry>
	<entry key="install.wizard.db.step.instructions.mysql"><![CDATA[<a target="_blank" href="https://openmeetings.apache.org/MySQLConfig.html">MySQL</a>]]></entry>
	<entry key="install.wizard.db.step.instructions.oracle"><![CDATA[<a target="_blank" href="https://openmeetings.apache.org/OracleConfig.html">Oracle</a>]]></entry>
	<entry key="install.wizard.db.step.instructions.postgresql"><![CDATA[<a target="_blank" href="https://openmeetings.apache.org/PostgresConfig.html">PostgreSql</a>]]></entry>
	<entry key="install.wizard.db.step.mssql.name"><![CDATA[MSSQL]]></entry>
	<entry key="install.wizard.db.step.mysql.name"><![CDATA[MySQL]]></entry>
	<entry key="install.wizard.db.step.nodriver"><![CDATA[Cannot load the proper DB driver. Please download the corresponding jar file and restart the OM server. Instructions: {0}]]></entry>
	<entry key="install.wizard.db.step.note"><![CDATA[<h4>
			<a id="Recommendation_for_production_environment"></a>Recommendation
			for production environment<a target="_blank"
				href="#Recommendation_for_production_environment"
				class="section_anchor"></a>
		</h4>
		<blockquote>
			By default {0} uses the integrated {1} database. For
			production environment you should consider using {2}, {3}, {4}, {5} or {6}
		</blockquote>
		<div class="alert alert-warning" role="alert">
			<p><strong>NOTE</strong> Please use unpredictable DB login and 'strong' password with length 8 characters or more.</p>
		</div>
	]]></entry>
	<entry key="install.wizard.db.step.notvalid"><![CDATA[Database check was unsuccessfull]]></entry>
	<entry key="install.wizard.db.step.oracle.name"><![CDATA[Oracle]]></entry>
	<entry key="install.wizard.db.step.pass"><![CDATA[Specify DB password]]></entry>
	<entry key="install.wizard.db.step.port"><![CDATA[Specify DB port]]></entry>
	<entry key="install.wizard.db.step.postgresql.name"><![CDATA[PostgreSql]]></entry>
	<entry key="install.wizard.db.step.user"><![CDATA[Specify DB user]]></entry>
	<entry key="install.wizard.db.step.valid"><![CDATA[Database check was successfull]]></entry>
	<entry key="install.wizard.install.desc"><![CDATA[Please click "Finish" button to start installation!]]></entry>
	<entry key="install.wizard.install.failed"><![CDATA[Installation has failed]]></entry>
	<entry key="install.wizard.install.started"><![CDATA[Please wait, installation in progress]]></entry>
	<entry key="install.wizard.installation"><![CDATA[Installation]]></entry>
	<entry key="install.wizard.params.step1.email.title"><![CDATA[Enter a EMail]]></entry>
	<entry key="install.wizard.params.step1.group"><![CDATA[Name]]></entry>
	<entry key="install.wizard.params.step1.group.title"><![CDATA[Enter a default Group]]></entry>
	<entry key="install.wizard.params.step1.groupdata"><![CDATA[Group(Domains)]]></entry>
	<entry key="install.wizard.params.step1.password"><![CDATA[Userpass]]></entry>
	<entry key="install.wizard.params.step1.password.title"><![CDATA[Enter a password]]></entry>
	<entry key="install.wizard.params.step1.tz"><![CDATA[User Time Zone]]></entry>
	<entry key="install.wizard.params.step1.userdata"><![CDATA[User data]]></entry>
	<entry key="install.wizard.params.step1.username"><![CDATA[Username]]></entry>
	<entry key="install.wizard.params.step1.username.title"><![CDATA[Enter a username]]></entry>
	<entry key="install.wizard.params.step2.allowFrontendRegister"><![CDATA[Allow self-registering]]></entry>
	<entry key="install.wizard.params.step2.configuration"><![CDATA[Configuration]]></entry>
	<entry key="install.wizard.params.step2.createDefaultObjects"><![CDATA[Default DB objects of all types will be created (including Rooms, OAuth2 servers etc.)]]></entry>
	<entry key="install.wizard.params.step2.defaultLangId"><![CDATA[Default Language]]></entry>
	<entry key="install.wizard.params.step2.mailAuthName"><![CDATA[SMTP-Username]]></entry>
	<entry key="install.wizard.params.step2.mailAuthName.title"><![CDATA[Enter the mail-username]]></entry>
	<entry key="install.wizard.params.step2.mailAuthPass"><![CDATA[SMTP-Userpass]]></entry>
	<entry key="install.wizard.params.step2.mailAuthPass.title"><![CDATA[Enter the mail-userpass]]></entry>
	<entry key="install.wizard.params.step2.mailReferer"><![CDATA[Mail-Referer]]></entry>
	<entry key="install.wizard.params.step2.mailReferer.title"><![CDATA[Enter a Referer]]></entry>
	<entry key="install.wizard.params.step2.mailUseTls"><![CDATA[Enable TLS in Mail Server Auth]]></entry>
	<entry key="install.wizard.params.step2.replyToOrganizer"><![CDATA[Set inviter's email
					address as ReplyTo in email invitations]]></entry>
	<entry key="install.wizard.params.step2.sendEmailAtRegister"><![CDATA[Send Email to new registered Users]]></entry>
	<entry key="install.wizard.params.step2.sendEmailWithVerficationCode"><![CDATA[New Users need to verify their EMail]]></entry>
	<entry key="install.wizard.params.step2.smtpPort"><![CDATA[SMTP-Server Port(default Smtp-Server Port is 25)]]></entry>
	<entry key="install.wizard.params.step2.smtpPort.title"><![CDATA[Enter a SMTP-Server.Port normally 25]]></entry>
	<entry key="install.wizard.params.step2.smtpServer"><![CDATA[SMTP-Server]]></entry>
	<entry key="install.wizard.params.step2.smtpServer.title"><![CDATA[Enter a SMTP-Server]]></entry>
	<entry key="install.wizard.params.step3.converters"><![CDATA[Converters]]></entry>
	<entry key="install.wizard.params.step3.docDpi"><![CDATA[Document conversion DPI]]></entry>
	<entry key="install.wizard.params.step3.docDpi.text"><![CDATA[DPI that ImageMagic will use for PDF to image conversion (default is 150)]]></entry>
	<entry key="install.wizard.params.step3.docDpi.title"><![CDATA[Enter the dpi that ImageMagic will use for PDF to image conversion]]></entry>
	<entry key="install.wizard.params.step3.docQuality"><![CDATA[Document conversion JPEG Quality]]></entry>
	<entry key="install.wizard.params.step3.docQuality.text"><![CDATA[Enter the quality of embedded jpeg pictures to quality. 0 is worst (small), 100 is best (big). (default:90)]]></entry>
	<entry key="install.wizard.params.step3.docQuality.title"><![CDATA[Enter the quality of embedded jpeg pictures to quality. 0 is worst (small), 100 is best (big). (default:90)]]></entry>
	<entry key="install.wizard.params.step3.ffmpegPath"><![CDATA[FFMPEG Path]]></entry>
	<entry key="install.wizard.params.step3.ffmpegPath.text"><![CDATA[Install fresh and up-to-date FFMpeg.]]></entry>
	<entry key="install.wizard.params.step3.ffmpegPath.title"><![CDATA[Enter the path to FFMPEG, leave blank if FFMPEG is installed to system-path]]></entry>
	<entry key="install.wizard.params.step3.imageMagicPath"><![CDATA[ImageMagick Path]]></entry>
	<entry key="install.wizard.params.step3.imageMagicPath.text"><![CDATA[Install ImageMagick on the server, you can get more information on http://www.imagemagick.org regarding installation. The instructions for installation can be found here http://www.imagemagick.org/script/binary-releases.php, however on most linux systems you can get it via the system's package manager (apt-get, dnf, yum etc)]]></entry>
	<entry key="install.wizard.params.step3.imageMagicPath.title"><![CDATA[Enter the path to ImageMagick, leave blank if ImageMagick is successfully installed to system-path]]></entry>
	<entry key="install.wizard.params.step3.officePath"><![CDATA[OpenOffice/LibreOffice Path for jodconverter]]></entry>
	<entry key="install.wizard.params.step3.officePath.text"><![CDATA[The path to OpenOffice/LibreOffice (optional) please set this to the real path in case jodconverter is unable to find OpenOffice/LibreOffice installation]]></entry>
	<entry key="install.wizard.params.step3.officePath.title"><![CDATA[The path to OpenOffice/LibreOffice (optional) please set this to the real path in case jodconverter is unable to find OpenOffice/LibreOffice installation automatically]]></entry>
	<entry key="install.wizard.params.step3.seeAlso"><![CDATA[ see also]]></entry>
	<entry key="install.wizard.params.step3.soxPath"><![CDATA[SoX Path]]></entry>
	<entry key="install.wizard.params.step3.soxPath.text"><![CDATA[Install SoX http://sox.sourceforge.net/ You should install SoX in a up to date copy! SoX 12.xx will NOT work!]]></entry>
	<entry key="install.wizard.params.step3.soxPath.title"><![CDATA[Enter the path to SoX, leave blank if SoX is successfully installed to system-path]]></entry>
	<entry key="install.wizard.params.step4.crypt"><![CDATA[Crypt Type]]></entry>
	<entry key="install.wizard.params.step4.cryptClassName"><![CDATA[Crypt Class]]></entry>
	<entry key="install.wizard.params.step4.cryptClassName.text"><![CDATA[You can use this default crypt type which is equal to
	RFC 7914 - The scrypt Password-Based Key Derivation Function:<b>org.apache.openmeetings.util.crypt.SCryptImplementation</b>
		for more information or to write your own Crypt-Style see: <a
		href="https://openmeetings.apache.org/CustomCryptMechanism.html"
		target="_blank">Custom Crypt Mechanism</a> You can edit this
		value later BUT previous created Users and Sessions might be not
		usable anymore
	]]></entry>
	<entry key="install.wizard.params.step4.cryptClassName.title"><![CDATA[Enter the Class name of the Encryption Class. DO NOT ALTER THIS IF YOU ARE NOT SURE]]></entry>
	<entry key="install.wizard.params.step4.sip"><![CDATA[red5SIP Configuration]]></entry>
	<entry key="install.wizard.params.step4.sipEnable"><![CDATA[Enable SIP]]></entry>
	<entry key="install.wizard.params.step4.sipEnable.text"><![CDATA[Enable red5SIP integration]]></entry>
	<entry key="install.wizard.params.step4.sipExtenContext"><![CDATA[SIP extensions context]]></entry>
	<entry key="install.wizard.params.step4.sipExtenContext.text"><![CDATA[Context of Asterisk extensions]]></entry>
	<entry key="install.wizard.params.step4.sipRoomPrefix"><![CDATA[SIP rooms prefix]]></entry>
	<entry key="install.wizard.params.step4.sipRoomPrefix.text"><![CDATA[Prefix for phone number of conference rooms]]></entry>
	<entry key="install.wizard.welcome.panel"><![CDATA[<ol>
		<li><h4>
				<a id="Enabling_import_of_PDFs_into_whiteboard"></a>Enabling
				import of PDFs into whiteboard<a
					href="#Enabling_import_of_PDFs_into_whiteboard"
					class="section_anchor"></a>
			</h4>
			<ul>
				<li>Install <strong>GhostScript</strong> on the server, you can
					get more information on <a target="_blank"
					href="http://pages.cs.wisc.edu/%7Eghost/" rel="nofollow">http://pages.cs.wisc.edu/~ghost/</a>
					regarding installation. The instructions for installation can be
					found there, however on most linux systems you can get it via your
					favorite package managers (apt-get it).
				</li>
			</ul>
		</li>
	</ol>

	<br />
	<b> <span class="installer-important">If you have further
			questions or need support in installation or hosting:</span></b>
	<br />
	<br />

	<b><span class="installer-important">Community-Support:</span></b>
	<br />
	<br />
	<span class="installer-less-important"><a
		href="https://openmeetings.apache.org/mailing-lists.html"
		target="_blank">Mailing lists</a></span>
	<br />
	<br />
	<b> <span class="installer-important">Commercial-Support:</span></b>
	<br />
	<br />
	<span class="installer-less-important"><a
		href="https://openmeetings.apache.org/commercial-support.html"
		target="_blank">Commercial-Support</a></span>

	<br />
	]]></entry>
	<entry key="internal.error"><![CDATA[Unfortunately something bad just happen :(, <br/>
please check <code>openmeetings.log</code> and contact OpenMeetings developers]]></entry>
	<entry key="invalid.hash"><![CDATA[Invalid hash]]></entry>
	<entry key="label.dock.panel"><![CDATA[Click to dock panel]]></entry>
	<entry key="label.end"><![CDATA[Koniec]]></entry>
	<entry key="label.hangup"><![CDATA[Hang-up]]></entry>
	<entry key="label.start"><![CDATA[Začiatok]]></entry>
	<entry key="label.undock.panel"><![CDATA[Click to undock panel]]></entry>
	<entry key="lbl.cancel"><![CDATA[Zrušiť]]></entry>
	<entry key="lbl.description"><![CDATA[Description]]></entry>
	<entry key="lbl.email"><![CDATA[Email]]></entry>
	<entry key="lbl.enter"><![CDATA[Vstup]]></entry>
	<entry key="lbl.general"><![CDATA[General]]></entry>
	<entry key="lbl.new"><![CDATA[new]]></entry>
	<entry key="lbl.or"><![CDATA[or]]></entry>
	<entry key="lbl.refresh"><![CDATA[Obnoviť]]></entry>
	<entry key="lbl.settings.whiteboard"><![CDATA[Whiteboard Settings]]></entry>
	<entry key="lbl.update"><![CDATA[Update]]></entry>
	<entry key="lbl.video"><![CDATA[Video]]></entry>
	<entry key="main.menu.admin.email"><![CDATA[Email management]]></entry>
	<entry key="main.menu.admin.email.desc"><![CDATA[Check e-mails processing by the system]]></entry>
	<entry key="main.menu.admin.extra"><![CDATA[Extra Menu]]></entry>
	<entry key="main.menu.admin.extra.desc"><![CDATA[Custom links to room menu]]></entry>
	<entry key="menu.extras"><![CDATA[Extras]]></entry>
	<entry key="menu.polls"><![CDATA[Polls]]></entry>
	<entry key="menu.polls.quick.descr"><![CDATA[Gather feedback without creating a poll]]></entry>
	<entry key="menu.polls.quick.title"><![CDATA[Create Quick Poll]]></entry>
	<entry key="messages.btn.reply"><![CDATA[Reply]]></entry>
	<entry key="messages.subject.re"><![CDATA[Re:]]></entry>
	<entry key="microphone.off"><![CDATA[Microphone is off. Click to turn on.]]></entry>
	<entry key="microphone.on"><![CDATA[Microphone is on. Click to turn off.]]></entry>
	<entry key="my.room.conference"><![CDATA[My conference room (for 1-16 users)]]></entry>
	<entry key="my.room.presentation"><![CDATA[My presentation room (for 1-120 users)]]></entry>
	<entry key="network.test.click.play"><![CDATA[Click the play button to run a test]]></entry>
	<entry key="network.test.copy.log"><![CDATA[Copy the log to the clipboard]]></entry>
	<entry key="network.test.dwn"><![CDATA[Download speed]]></entry>
	<entry key="network.test.dwn.bytes"><![CDATA[Bytes downloaded]]></entry>
	<entry key="network.test.dwn.speed"><![CDATA[Download speed]]></entry>
	<entry key="network.test.dwn.time"><![CDATA[Download time]]></entry>
	<entry key="network.test.jitter"><![CDATA[Jitter]]></entry>
	<entry key="network.test.jitter.avg"><![CDATA[Average time]]></entry>
	<entry key="network.test.jitter.avgAbbr"><![CDATA[Avg.]]></entry>
	<entry key="network.test.jitter.max"><![CDATA[Max time]]></entry>
	<entry key="network.test.jitter.min"><![CDATA[Min time]]></entry>
	<entry key="network.test.mb"><![CDATA[Mb]]></entry>
	<entry key="network.test.ms"><![CDATA[ms]]></entry>
	<entry key="network.test.ping"><![CDATA[Ping]]></entry>
	<entry key="network.test.ping.avg"><![CDATA[Average ping time]]></entry>
	<entry key="network.test.ping.load"><![CDATA[load time]]></entry>
	<entry key="network.test.ping.lost"><![CDATA[Packets lost]]></entry>
	<entry key="network.test.ping.rcv"><![CDATA[Packets received]]></entry>
	<entry key="network.test.port"><![CDATA[Port]]></entry>
	<entry key="network.test.port.avail"><![CDATA[port is available]]></entry>
	<entry key="network.test.port.stopped"><![CDATA[stopped]]></entry>
	<entry key="network.test.report.start"><![CDATA[start test...]]></entry>
	<entry key="network.test.sec"><![CDATA[sec]]></entry>
	<entry key="network.test.upl"><![CDATA[Upload speed]]></entry>
	<entry key="network.test.upl.bytes"><![CDATA[Bytes uploaded]]></entry>
	<entry key="network.test.upl.speed"><![CDATA[Upload speed]]></entry>
	<entry key="network.test.upl.time"><![CDATA[Upload time]]></entry>
	<entry key="notification.chat.message"><![CDATA[You have new chat message(s)]]></entry>
	<entry key="notification.room.activity"><![CDATA[You have new activities, please check "Activities&Action"]]></entry>
	<entry key="otp.disable"><![CDATA[Disable One Time Password]]></entry>
	<entry key="otp.disable.confirm"><![CDATA[Are you sure you want to disable OTP? Security level will be lowered.]]></entry>
	<entry key="otp.enable"><![CDATA[Enable One Time Password]]></entry>
	<entry key="otp.enabled"><![CDATA[One Time Password enabled]]></entry>
	<entry key="otp.fallback.desc"><![CDATA[Please save these one-time codes in secret place, they can be used in case you will loose access to your mobile device.]]></entry>
	<entry key="otp.fallback.invalid"><![CDATA[Wrong Recovery code]]></entry>
	<entry key="otp.fallback.label"><![CDATA[Recovery code]]></entry>
	<entry key="otp.invalid"><![CDATA[Wrong One Time Password]]></entry>
	<entry key="otp.label"><![CDATA[One Time Password]]></entry>
	<entry key="otp.qr.desc"><![CDATA[Please open Google Authenticator and scan this QR code]]></entry>
	<entry key="poll.clone"><![CDATA[Clone]]></entry>
	<entry key="poll.type.NUMERIC"><![CDATA[Čísla 1-10]]></entry>
	<entry key="poll.type.YES_NO"><![CDATA[Áno/Nie]]></entry>
	<entry key="profile.invitation"><![CDATA[Invitation]]></entry>
	<entry key="profile.invitations"><![CDATA[Invitations]]></entry>
	<entry key="ptt.info"><![CDATA[Your microphone is muted. You can hold Ctrl+Space (Cmd+Space) to temporary unmute it (Push-to-Talk)]]></entry>
	<entry key="recordings.root.group"><![CDATA[Group recordings]]></entry>
	<entry key="register.privacy.accept"><![CDATA[By clicking "${register}", you agree to our ${link}.]]></entry>
	<entry key="register.privacy.statement"><![CDATA[privacy statement]]></entry>
	<entry key="reset.whiteboard"><![CDATA[Reset Whiteboard]]></entry>
	<entry key="restricted.group.files"><![CDATA[Group files are restricted]]></entry>
	<entry key="room.type.CONFERENCE"><![CDATA[conference (1-25 users)]]></entry>
	<entry key="room.type.CONFERENCE.desc"><![CDATA["democratic" by default, every user can directly enable audio/video without need for asking]]></entry>
	<entry key="room.type.INTERVIEW"><![CDATA[interview (1:1 meeting with recording)]]></entry>
	<entry key="room.type.INTERVIEW.desc"><![CDATA[only 2 users can have audio/video enabled (more users can be in the room and you can switch the audio/video between them of course)]]></entry>
	<entry key="room.type.PRESENTATION"><![CDATA[presentation (1-150 users)]]></entry>
	<entry key="room.type.PRESENTATION.desc"><![CDATA["restricted" by default: Every regular user will need to ask if he wants to share audio/video]]></entry>
	<entry key="save.success"><![CDATA[Saved successfully]]></entry>
	<entry key="send.on.ctrl.enter"><![CDATA[Send on Ctrl+Enter]]></entry>
	<entry key="send.on.enter"><![CDATA[Send on Enter]]></entry>
	<entry key="sound.enable"><![CDATA[Enable sound]]></entry>
	<entry key="sound.mute"><![CDATA[Mute sound]]></entry>
	<entry key="template.new.group.users.notification.body"><![CDATA[Dear "{0}" group moderator,<br/>
<br/>
{1} new users were added to the group in the last {2} hours<br/>
Please visit {3} OM server and check them under Admin -> Groups]]></entry>
	<entry key="template.new.group.users.notification.footer"><![CDATA[Regards,<br/>
{0} Support Team.]]></entry>
	<entry key="template.new.group.users.notification.subject"><![CDATA[[{0}] New "{1}" group users]]></entry>
	<entry key="template.recording.expiring.body"><![CDATA[Your recent {0} recording will be automatically deleted
		in {1} days. If you would like to save this recording, please download it before then.]]></entry>
	<entry key="template.recording.expiring.footer"><![CDATA[Regards,<br/>
	{0} Support Team.]]></entry>
	<entry key="template.recording.expiring.greetings"><![CDATA[Hello {0}]]></entry>
	<entry key="template.recording.expiring.subj.prefix"><![CDATA[Recording will be deleted]]></entry>
	<entry key="template.recording.expiring.subj.room"><![CDATA[ -- Room[{0}]]]></entry>
	<entry key="template.recording.invitation.text"><![CDATA[Click this link to view the conference recording video. [The link may only work for a certain period.]]]></entry>
	<entry key="template.room.invitation.text"><![CDATA[Pre participáciu v tejto miestnosti kliknite na tento link:]]></entry>
	<entry key="ulist.right.audio.grant"><![CDATA[Allow this user to use microphone]]></entry>
	<entry key="ulist.right.audio.request"><![CDATA[Request permission to use microphone]]></entry>
	<entry key="ulist.right.audio.revoke"><![CDATA[Mute user and remove the right to turn on microphone]]></entry>
	<entry key="ulist.right.moderator.grant"><![CDATA[Allow this user to be moderator]]></entry>
	<entry key="ulist.right.moderator.request"><![CDATA[Request moderator permissions]]></entry>
	<entry key="ulist.right.moderator.revoke"><![CDATA[Remove moderator permissions from this user]]></entry>
	<entry key="ulist.right.muteothers.grant"><![CDATA[Allow this user to mute others]]></entry>
	<entry key="ulist.right.muteothers.request"><![CDATA[Request permission to mute others]]></entry>
	<entry key="ulist.right.muteothers.revoke"><![CDATA[Remove this user's right to mute others]]></entry>
	<entry key="ulist.right.presenter.grant"><![CDATA[Allow this user to be a presenter]]></entry>
	<entry key="ulist.right.presenter.request"><![CDATA[Request presenter permissions]]></entry>
	<entry key="ulist.right.presenter.revoke"><![CDATA[Remove presenter permissions from this user]]></entry>
	<entry key="ulist.right.remote.grant"><![CDATA[Allow Remote Control (during screen sharing)]]></entry>
	<entry key="ulist.right.remote.request"><![CDATA[Request remote control permission (during screen sharing)]]></entry>
	<entry key="ulist.right.remote.revoke"><![CDATA[Remove user's Remote Control permission (during screen sharing)]]></entry>
	<entry key="ulist.right.share.grant"><![CDATA[Allow user to share screen/record]]></entry>
	<entry key="ulist.right.share.request"><![CDATA[Request permission to share/record screen]]></entry>
	<entry key="ulist.right.share.revoke"><![CDATA[Remove user's screenshare/record permission]]></entry>
	<entry key="ulist.right.video.grant"><![CDATA[Allow user to use camera]]></entry>
	<entry key="ulist.right.video.request"><![CDATA[Request permission to use camera]]></entry>
	<entry key="ulist.right.video.revoke"><![CDATA[Turn off user's camera and remove permission]]></entry>
	<entry key="ulist.right.wb.grant"><![CDATA[Allow this user to draw on the whiteboard]]></entry>
	<entry key="ulist.right.wb.request"><![CDATA[Request permission to draw on the whiteboard]]></entry>
	<entry key="ulist.right.wb.revoke"><![CDATA[Remove this user's permission to draw on the whiteboard]]></entry>
	<entry key="ulist.user.muteothers"><![CDATA[ (By clicking here you can mute the microphone of others)]]></entry>
	<entry key="ulist.user.muteothers.confirm"><![CDATA[Do you really want to mute all users except this one?]]></entry>
	<entry key="ulist.user.speaks"><![CDATA[používateľ hovorí]]></entry>
	<entry key="upload.dlg.choose.title"><![CDATA[Vybrať súbor]]></entry>
	<entry key="upload.dlg.convert.title"><![CDATA[Converting...]]></entry>
	<entry key="user.label.displayName"><![CDATA[Display name]]></entry>
	<entry key="user.salutation.DR"><![CDATA[Dr]]></entry>
	<entry key="user.salutation.MR"><![CDATA[Pán]]></entry>
	<entry key="user.salutation.MRS"><![CDATA[Pani]]></entry>
	<entry key="user.salutation.MS"><![CDATA[Pani]]></entry>
	<entry key="user.salutation.PROF"><![CDATA[Prof]]></entry>
	<entry key="video.mic.off"><![CDATA[Microphone is muted]]></entry>
	<entry key="video.mic.on"><![CDATA[Microphone is on!]]></entry>
	<entry key="video.muteothers"><![CDATA[Mute microphone of others]]></entry>
	<entry key="video.permission.text"><![CDATA[Extra permission is required to play video.<br/>Press OK to allow playing.]]></entry>
	<entry key="video.permission.title"><![CDATA[Permission is required]]></entry>
	<entry key="video.settings.https.required"><![CDATA[Camera/microphone most probably will not work in insecure environment. Try using https.]]></entry>
	<entry key="volume.label"><![CDATA[Adjust volume]]></entry>
	<entry key="wait-moderator.message"><![CDATA[Please wait until a <b>moderator</b> enters the room]]></entry>
	<entry key="wait-moderator.title"><![CDATA[Please be patient ...]]></entry>
	<entry key="warn.nogroup"><![CDATA[Používateľ pridaný, ale je nutné priradiť ho k spoločnosti.]]></entry>
	<entry key="warn.notverified"><![CDATA[You have successfully signed up. An email with a verification code will be sent to your mailbox.]]></entry>
	<entry key="wb.add.whiteboard"><![CDATA[Add new whiteboard to conference room]]></entry>
	<entry key="wb.next.whiteboard"><![CDATA[Scroll whiteboard tabbar left]]></entry>
	<entry key="wb.pre.whiteboard"><![CDATA[Scroll whiteboard tabbar right]]></entry>
	<entry key="wb.tool.math.formula"><![CDATA[Math formula]]></entry>
	<entry key="wb.tool.math.guide.lbl"><![CDATA[Guide to LaTeX Syntax]]></entry>
	<entry key="wb.tool.math.guide.url"><![CDATA[https://en.wikibooks.org/wiki/LaTeX/Mathematics]]></entry>
	<entry key="wb.tool.redo"><![CDATA[Redo]]></entry>
	<entry key="wb.tool.undo"><![CDATA[Zrušiť]]></entry>
	<entry key="wb.tool.white-out"><![CDATA[White-Out]]></entry>
	<entry key="widget.recent.desc"><![CDATA[This sections displays rooms recently opened by you]]></entry>
	<entry key="widget.recent.title"><![CDATA[Recent Rooms]]></entry>
	<entry key="widget.start.desc"><![CDATA[{0}, your web conferencing platform. You can either follow the 1-2-3 steps to enter a conference room directly or you choose the Calendar to set up a meeting.]]></entry>
	<entry key="widget.start.header"><![CDATA[Ako konferencovať:]]></entry>
	<entry key="widget.start.title"><![CDATA[Getting Started]]></entry>
	<entry key="wizard.button.finish"><![CDATA[Finish]]></entry>
	<entry key="zoom.FULL_FIT"><![CDATA[Napasovanie]]></entry>
	<entry key="zoom.PAGE_WIDTH"><![CDATA[Page Width]]></entry>
</properties>
